src/subtractor.v
module SUB (
    output reg [15:0] out,
    input [15:0] in1,
    input [15:0] in2
);
// The (*) means this block triggers anytime in1 or in2 changes
    always @(*) begin
        out = in1 - in2;
    end
endmodule

src/comparator.v
module COMPARE (
    output lt, gt, eq,
    input [15:0] data1, 
    input [15:0] data2
);
    // Continuous assignment for simple logic checks
    assign lt = (data1 < data2);
    assign gt = (data1 > data2);
    assign eq = (data1 == data2);
endmodule

src/mux.v
module MUX (
    output [15:0] out,
    input [15:0] in0,
    input [15:0] in1,
    input sel
);
    // If sel is 0, output in0. If sel is 1, output in1.
    assign out = sel ? in1 : in0;
endmodule

src/pipo.v
module PIPO (
    output reg [15:0] data_out,
    input [15:0] data_in,
    input load, 
    input clk
);
    // On the rising edge of the clock, 
    // if 'load' is high, the data is saved into the register.
    always @(posedge clk) begin
        if (load)
            data_out <= data_in;
    end
endmodule

src/gcf_datapath.v
module GCF_datapath (
    output wire lt, gt, eq,          
    input wire [15:0] data_in,       
    input wire ldA, ldB,             
    input wire sel1, sel2, sel_in,   
    input wire clk
);

    // Internal wires
    wire [15:0] Aout, Bout;
    wire [15:0] x, y;
    wire [15:0] Subout;
    wire [15:0] bus_in;

    MUX MUX_load (
        .out(bus_in), 
        .in0(Subout), 
        .in1(data_in), 
        .sel(sel_in)
    );

    PIPO Reg_A (
        .data_out(Aout), 
        .data_in(bus_in), 
        .load(ldA), 
        .clk(clk)
    );
    
    PIPO Reg_B (
        .data_out(Bout), 
        .data_in(bus_in), 
        .load(ldB), 
        .clk(clk)
    );

    MUX MUX_IN1 (
        .out(x), 
        .in0(Aout), 
        .in1(Bout), 
        .sel(sel1)
    );
    
    MUX MUX_IN2 (
        .out(y), 
        .in0(Aout), 
        .in1(Bout), 
        .sel(sel2)
    );

    COMPARE COMP (
        .lt(lt), 
        .gt(gt), 
        .eq(eq), 
        .data1(Aout), 
        .data2(Bout)
    );

    SUB SB (
        .out(Subout), 
        .in1(x), 
        .in2(y)
    );

endmodule

src/controller.v
module GCF_controller (
    input clk, reset, start,
    input lt, gt, eq,
    output reg ldA, ldB, sel1, sel2, sel_in,
    output reg done
);
    // Define states using localparam for clarity
    localparam S0 = 3'b000, // Wait for start
               S1 = 3'b001, // Load A
               S2 = 3'b010, // Load B
               S3 = 3'b011, // Compare and Select Path
               S4 = 3'b100, // Update A (A = A - B)
               S5 = 3'b101, // Update B (B = B - A)
               S6 = 3'b110; // Done

    reg [2:0] state;

    always @(posedge clk) begin
        if (reset) begin
            state <= S0;
        end else begin
            case (state)
                S0: if (start) state <= S1;
                S1: state <= S2;
                S2: state <= S3;
                S3: begin
                    if (eq) state <= S6;
                    else if (lt) state <= S5; // B is bigger
                    else if (gt) state <= S4; // A is bigger
                end
                S4: state <= S3; // Return to compare
                S5: state <= S3; // Return to compare
                S6: if (!start) state <= S0;
                default: state <= S0;
            endcase
        end
    end

    // Control Logic (Outputs based on current state)
    always @(*) begin
        // Default values to avoid latches
        ldA = 0; ldB = 0; sel1 = 0; sel2 = 0; sel_in = 0; done = 0;
        
        case (state)
            S1: begin ldA = 1; sel_in = 1; end // Initial Load A from data_in
            S2: begin ldB = 1; sel_in = 1; end // Initial Load B from data_in
            S4: begin // A = A - B
                sel1 = 0; // Select Aout
                sel2 = 1; // Select Bout
                ldA = 1;  // Load result into A
                sel_in = 0; // Take result from Subtractor
            end
            S5: begin // B = B - A
                sel1 = 1; // Select Bout
                sel2 = 0; // Select Aout
                ldB = 1;  // Load result into B
                sel_in = 0; // Take result from Subtractor
            end
            S6: done = 1;
        endcase
    end
endmodule

src/gcf_top.v
module GCF_Top (
    input clk,
    input reset,
    input start,
    input [15:0] data_in,
    output done
);

    // Internal wires acting as the "nervous system" between Brain and Body
    wire lt, gt, eq;
    wire ldA, ldB, sel1, sel2, sel_in;

    // 1. Instantiate the Brain (Controller)
    GCF_controller controller_inst (
        .clk(clk),
        .reset(reset),
        .start(start),
        .lt(lt),
        .gt(gt),
        .eq(eq),
        .ldA(ldA),
        .ldB(ldB),
        .sel1(sel1),
        .sel2(sel2),
        .sel_in(sel_in),
        .done(done)
    );

    // 2. Instantiate the Body (Datapath)
    GCF_datapath datapath_inst (
        .clk(clk),
        .data_in(data_in),
        .ldA(ldA),
        .ldB(ldB),
        .sel1(sel1),
        .sel2(sel2),
        .sel_in(sel_in),
        .lt(lt),
        .gt(gt),
        .eq(eq)
    );

endmodule

tb/gcf_tb.v
`timescale 1ns / 1ps

module gcf_tb;

    reg clk;
    reg reset;
    reg start;
    reg [15:0] data_in;
    wire done;

    // Instantiate the Top Module
    GCF_Top uut (
        .clk(clk),
        .reset(reset),
        .start(start),
        .data_in(data_in),
        .done(done)
    );

    // Generate a clock (10ns period)
    always #5 clk = ~clk;

    initial begin
        // GTKWave Setup
        $dumpfile("gcf_sim.vcd");
        $dumpvars(0, gcf_tb);

        // 1. Initialize System
        clk = 0;
        reset = 1;
        start = 0;
        data_in = 0;

        // 2. Release Reset
        #10 reset = 0;

        // 3. Pulse the Start button
        #10 start = 1;

        // 4. Feed Input A (Wait for FSM to enter State 1)
        #10 data_in = 16'd15; 

        // 5. Feed Input B (Wait for FSM to enter State 2)
        #10 data_in = 16'd10; 
        
        // Turn off start switch so it doesn't loop infinitely
        #10 start = 0;        

        // 6. Wait for the 'done' signal to go HIGH
        wait(done == 1);
        #10;
        
        // This will print the result as text in your terminal
        $display("----------------------------------------------");
        $display("GCF Calculation Complete!");
        $display("Final Result in Register A: %d", uut.datapath_inst.Aout);
        $display("Final Result in Register B: %d", uut.datapath_inst.Bout);
        $display("----------------------------------------------");
        $finish;
    end

endmodule

gcf_sim.vcd
$date
	Sat May 02 12:30:37 2026
$end
$version
	Icarus Verilog
$end
$timescale
	1ps
$end
$scope module gcf_tb $end
$var wire 1 ! done $end
$var reg 1 " clk $end
$var reg 16 # data_in [15:0] $end
$var reg 1 $ reset $end
$var reg 1 % start $end
$scope module uut $end
$var wire 1 " clk $end
$var wire 16 & data_in [15:0] $end
$var wire 1 $ reset $end
$var wire 1 % start $end
$var wire 1 ' sel_in $end
$var wire 1 ( sel2 $end
$var wire 1 ) sel1 $end
$var wire 1 * lt $end
$var wire 1 + ldB $end
$var wire 1 , ldA $end
$var wire 1 - gt $end
$var wire 1 . eq $end
$var wire 1 ! done $end
$scope module controller_inst $end
$var wire 1 " clk $end
$var wire 1 $ reset $end
$var wire 1 % start $end
$var wire 1 * lt $end
$var wire 1 - gt $end
$var wire 1 . eq $end
$var parameter 3 / S0 $end
$var parameter 3 0 S1 $end
$var parameter 3 1 S2 $end
$var parameter 3 2 S3 $end
$var parameter 3 3 S4 $end
$var parameter 3 4 S5 $end
$var parameter 3 5 S6 $end
$var reg 1 ! done $end
$var reg 1 , ldA $end
$var reg 1 + ldB $end
$var reg 1 ) sel1 $end
$var reg 1 ( sel2 $end
$var reg 1 ' sel_in $end
$var reg 3 6 state [2:0] $end
$upscope $end
$scope module datapath_inst $end
$var wire 1 " clk $end
$var wire 16 7 data_in [15:0] $end
$var wire 1 , ldA $end
$var wire 1 + ldB $end
$var wire 1 ) sel1 $end
$var wire 1 ( sel2 $end
$var wire 1 ' sel_in $end
$var wire 16 8 y [15:0] $end
$var wire 16 9 x [15:0] $end
$var wire 1 * lt $end
$var wire 1 - gt $end
$var wire 1 . eq $end
$var wire 16 : bus_in [15:0] $end
$var wire 16 ; Subout [15:0] $end
$var wire 16 < Bout [15:0] $end
$var wire 16 = Aout [15:0] $end
$scope module COMP $end
$var wire 1 * lt $end
$var wire 1 - gt $end
$var wire 1 . eq $end
$var wire 16 > data2 [15:0] $end
$var wire 16 ? data1 [15:0] $end
$upscope $end
$scope module MUX_IN1 $end
$var wire 1 ) sel $end
$var wire 16 @ out [15:0] $end
$var wire 16 A in1 [15:0] $end
$var wire 16 B in0 [15:0] $end
$upscope $end
$scope module MUX_IN2 $end
$var wire 1 ( sel $end
$var wire 16 C out [15:0] $end
$var wire 16 D in1 [15:0] $end
$var wire 16 E in0 [15:0] $end
$upscope $end
$scope module MUX_load $end
$var wire 16 F in1 [15:0] $end
$var wire 1 ' sel $end
$var wire 16 G out [15:0] $end
$var wire 16 H in0 [15:0] $end
$upscope $end
$scope module Reg_A $end
$var wire 1 " clk $end
$var wire 16 I data_in [15:0] $end
$var wire 1 , load $end
$var reg 16 J data_out [15:0] $end
$upscope $end
$scope module Reg_B $end
$var wire 1 " clk $end
$var wire 16 K data_in [15:0] $end
$var wire 1 + load $end
$var reg 16 L data_out [15:0] $end
$upscope $end
$scope module SB $end
$var wire 16 M in1 [15:0] $end
$var wire 16 N in2 [15:0] $end
$var reg 16 O out [15:0] $end
$upscope $end
$upscope $end
$upscope $end
$upscope $end
$enddefinitions $end
$comment Show the parameter values. $end
$dumpall
b110 5
b101 4
b100 3
b11 2
b10 1
b1 0
b0 /
$end
#0
$dumpvars
bx O
bx N
bx M
bx L
bx K
bx J
bx I
bx H
bx G
b0 F
bx E
bx D
bx C
bx B
bx A
bx @
bx ?
bx >
bx =
bx <
bx ;
bx :
bx 9
bx 8
b0 7
bx 6
x.
x-
x,
x+
x*
x)
x(
x'
b0 &
0%
1$
b0 #
0"
x!
$end
#5000
0!
0'
0(
0)
0+
0,
b0 6
1"
#10000
0"
0$
#15000
1"
#20000
0"
1%
#25000
b0 :
b0 G
b0 I
b0 K
1'
1,
b1 6
1"
#30000
b1111 :
b1111 G
b1111 I
b1111 K
0"
b1111 #
b1111 &
b1111 7
b1111 F
#35000
b0 ;
b0 H
b0 O
b1111 8
b1111 C
b1111 N
b1111 9
b1111 @
b1111 M
1+
1'
0,
b1111 =
b1111 ?
b1111 B
b1111 E
b1111 J
b10 6
1"
#40000
b1010 :
b1010 G
b1010 I
b1010 K
0"
b1010 #
b1010 &
b1010 7
b1010 F
#45000
b0 :
b0 G
b0 I
b0 K
0'
0+
b11 6
0.
1-
0*
b1010 <
b1010 >
b1010 A
b1010 D
b1010 L
1"
#50000
0"
0%
#55000
b101 :
b101 G
b101 I
b101 K
b101 ;
b101 H
b101 O
b1010 8
b1010 C
b1010 N
1,
1(
b100 6
1"
#60000
0"
#65000
b0 :
b0 G
b0 I
b0 K
b101 8
b101 C
b101 N
b0 ;
b0 H
b0 O
0(
0,
b101 9
b101 @
b101 M
b11 6
0-
1*
b101 =
b101 ?
b101 B
b101 E
b101 J
1"
#70000
0"
#75000
b101 :
b101 G
b101 I
b101 K
b101 ;
b101 H
b101 O
b1010 9
b1010 @
b1010 M
1+
1)
b101 6
1"
#80000
0"
#85000
b0 :
b0 G
b0 I
b0 K
b0 ;
b0 H
b0 O
0)
0+
b101 9
b101 @
b101 M
b11 6
1.
0*
b101 <
b101 >
b101 A
b101 D
b101 L
1"
#90000
0"
#95000
1!
b110 6
1"
#100000
0"
#105000
0!
b0 6
1"
